bill_pkg/__init__.py
bill_pkg/bill.py
eiBill_hieukien-0.0.6.dist-info/METADATA
eiBill_hieukien-0.0.6.dist-info/WHEEL
eiBill_hieukien-0.0.6.dist-info/top_level.txt
eiBill_hieukien-0.0.6.dist-info/RECORD
