Metadata-Version: 2.1
Name: eiBill-hieukien
Version: 0.0.6
Summary: SmartDoc package - OCR and Extract Informations Vietnamese Documents
Home-page: https://github.com/pypa/sampleproject
Author: hieukien
Author-email: hieukien82@gmail.com
License: UNKNOWN
Project-URL: Bug Tracker, https://github.com/pypa/sampleproject/issues
Platform: UNKNOWN
Classifier: Programming Language :: Python :: 3
Classifier: License :: OSI Approved :: MIT License
Classifier: Operating System :: OS Independent
Requires-Python: >=3.6
